prompt_manager_cli/__init__.py
prompt_manager_cli/__main__.py
prompt_manager_cli/cli.py
prompt_manager_cli/utils.py
prompt_manager_cli-0.1.3.dist-info/METADATA
prompt_manager_cli-0.1.3.dist-info/WHEEL
prompt_manager_cli-0.1.3.dist-info/entry_points.txt
prompt_manager_cli-0.1.3.dist-info/top_level.txt
prompt_manager_cli-0.1.3.dist-info/RECORD
