Metadata-Version: 2.4
Name: prompt-manager-cli
Version: 0.1.3
Summary: A CLI tool to create and organize prompt files for code agents.
Author-email: Your Name <you@example.com>
License-Expression: MIT
Project-URL: Homepage, https://github.com/yourusername/prompt-manager-cli
Project-URL: Repository, https://github.com/yourusername/prompt-manager-cli
Keywords: cli,prompts,ai,llm,developer-tools
Classifier: Development Status :: 3 - Alpha
Classifier: Environment :: Console
Classifier: Intended Audience :: Developers
Classifier: Programming Language :: Python :: 3
Classifier: Programming Language :: Python :: 3.9
Classifier: Programming Language :: Python :: 3.10
Classifier: Programming Language :: Python :: 3.11
Classifier: Programming Language :: Python :: 3.12
Classifier: Programming Language :: Python :: 3.13
Classifier: Topic :: Software Development :: Libraries :: Python Modules
Requires-Python: >=3.9
Requires-Dist: typer>=0.9.0
Requires-Dist: rich>=13.0.0
Provides-Extra: dev
Requires-Dist: pytest>=7.0.0; extra == "dev"
Requires-Dist: pytest-cov>=4.0.0; extra == "dev"
